chatgpt_mirai_qq_bot_onebot_adapter-0.3.0.post1.dist-info/licenses/LICENSE
im_onebot_adapters/__init__.py
im_onebot_adapters/adapter.py
im_onebot_adapters/config.py
im_onebot_adapters/assets/onebot.png
im_onebot_adapters/events/__init__.py
im_onebot_adapters/events/operation_event.py
im_onebot_adapters/handlers/__init__.py
im_onebot_adapters/handlers/message_result.py
im_onebot_adapters/utils/__init__.py
im_onebot_adapters/utils/message.py
chatgpt_mirai_qq_bot_onebot_adapter-0.3.0.post1.dist-info/METADATA
chatgpt_mirai_qq_bot_onebot_adapter-0.3.0.post1.dist-info/WHEEL
chatgpt_mirai_qq_bot_onebot_adapter-0.3.0.post1.dist-info/entry_points.txt
chatgpt_mirai_qq_bot_onebot_adapter-0.3.0.post1.dist-info/top_level.txt
chatgpt_mirai_qq_bot_onebot_adapter-0.3.0.post1.dist-info/RECORD
