Metadata-Version: 2.4
Name: chatgpt-mirai-qq-bot-onebot-adapter
Version: 0.3.0.post1
Summary: OneBot adapter for Kirara AI
Home-page: https://github.com/cloxl/chatgpt-mirai-qq-bot-onebot-adapter
Author: Cloxl
Author-email: cloxl2017@outlook.at
Project-URL: Bug Tracker, https://github.com/cloxl/chatgpt-mirai-qq-bot-onebot-adapter/issues
Project-URL: Documentation, https://oa-docs.cloxl.com
Project-URL: Source Code, https://github.com/cloxl/chatgpt-mirai-qq-bot-onebot-adapter
Classifier: Programming Language :: Python :: 3
Classifier: License :: OSI Approved :: GNU Affero General Public License v3
Classifier: Operating System :: OS Independent
Requires-Python: >=3.8
License-File: LICENSE
Requires-Dist: aiocqhttp[all]>=1.4.4
Requires-Dist: kirara-ai>=3.2.0a1
Dynamic: author
Dynamic: author-email
Dynamic: classifier
Dynamic: description
Dynamic: description-content-type
Dynamic: home-page
Dynamic: license-file
Dynamic: project-url
Dynamic: requires-dist
Dynamic: requires-python
Dynamic: summary
